MANIFEST.in
setup.cfg
setup.py
pokershell/__init__.py
pokershell/config.py
pokershell/intro.py
pokershell/model.py
pokershell/parser.py
pokershell/shell.py
pokershell/utils.py
pokershell.egg-info/PKG-INFO
pokershell.egg-info/SOURCES.txt
pokershell.egg-info/dependency_links.txt
pokershell.egg-info/entry_points.txt
pokershell.egg-info/namespace_packages.txt
pokershell.egg-info/not-zip-safe
pokershell.egg-info/pbr.json
pokershell.egg-info/top_level.txt
pokershell/eval/__init__.py
pokershell/eval/bet.py
pokershell/eval/context.py
pokershell/eval/evaluators.py
pokershell/eval/game.py
pokershell/eval/manager.py
pokershell/eval/simulation.py
pokershell/eval/preflop/10.txt
pokershell/eval/preflop/2.txt
pokershell/eval/preflop/3.txt
pokershell/eval/preflop/4.txt
pokershell/eval/preflop/5.txt
pokershell/eval/preflop/6.txt
pokershell/eval/preflop/7.txt
pokershell/eval/preflop/8.txt
pokershell/eval/preflop/9.txt
pokershell/tests/__init__.py
pokershell/tests/test_config.py
pokershell/tests/test_model.py
pokershell/tests/test_parser.py
pokershell/tests/test_shell.py
pokershell/tests/eval/__init__.py
pokershell/tests/eval/common.py
pokershell/tests/eval/test_bet.py
pokershell/tests/eval/test_context.py
pokershell/tests/eval/test_evaluators.py
pokershell/tests/eval/test_game.py
pokershell/tests/eval/test_manager.py
pokershell/tests/eval/test_simulation.py