Metadata-Version: 1.1
Name: pokershell
Version: 0.1.5
Summary: Poker Shell - Texas hold 'em command line calculator and simulator
Home-page: https://github.com/fblaha/pokershell
Author: Filip Blaha
Author-email: blahaf@gmail.com
License: UNKNOWN
Keywords: poker
Platform: Any
Classifier: Environment :: Console
